sage_deps-0.1.2.dist-info/licenses/LICENSE
sagedeps/__init__.py
sagedeps/constants.py
sagedeps/main.py
sagedeps/sage_hist.py
sagedeps/analysis/__init__.py
sagedeps/analysis/betweeness.py
sagedeps/analysis/cliques.py
sagedeps/analysis/clustering.py
sagedeps/analysis/cycles.py
sagedeps/analysis/distance.py
sagedeps/analysis/graph_analysis.py
sagedeps/analysis/page_rank.py
sagedeps/analysis/stability.py
sagedeps/deps/__init__.py
sagedeps/deps/data.py
sagedeps/deps/graphics.py
sagedeps/deps/loader.py
sagedeps/deps/parser.py
sagedeps/deps/score.py
sagedeps/deps/filter/__init__.py
sagedeps/deps/filter/balance.py
sagedeps/deps/filter/connectors.py
sagedeps/deps/filter/degree_filter.py
sagedeps/deps/filter/depth_filter.py
sagedeps/deps/filter/distance_filter.py
sagedeps/deps/filter/filter.py
sagedeps/deps/filter/loader.py
sagedeps/deps/filter/path_filter.py
sagedeps/deps/filter/score_filter.py
sagedeps/deps/model/__init__.py
sagedeps/deps/model/dependency.py
sagedeps/deps/model/importable.py
sagedeps/deps/model/module.py
sagedeps/deps/model/sageclass.py
sagedeps/hist/__init__.py
sagedeps/hist/pydrill.py
sage_deps-0.1.2.dist-info/METADATA
sage_deps-0.1.2.dist-info/WHEEL
sage_deps-0.1.2.dist-info/entry_points.txt
sage_deps-0.1.2.dist-info/top_level.txt
sage_deps-0.1.2.dist-info/RECORD
