Metadata-Version: 2.4
Name: sage-deps
Version: 0.1.2
Summary: Sage Deps
Author-email: Andrew Luo <j92luo@uwaterloo.ca>
Requires-Python: >=3.7
License-File: LICENSE
Dynamic: license-file
